adv_optm/__init__.py
adv_optm/optim/AdaMuon_adv.py
adv_optm/optim/AdamW_adv.py
adv_optm/optim/Adopt_adv.py
adv_optm/optim/Lion_Prodigy_adv.py
adv_optm/optim/Lion_adv.py
adv_optm/optim/Muon_adv.py
adv_optm/optim/Prodigy_adv.py
adv_optm/optim/SignSGD_adv.py
adv_optm/optim/Simplified_AdEMAMix.py
adv_optm/optim/__init__.py
adv_optm/util/Kourkoutas.py
adv_optm/util/Muon_AuxAdam.py
adv_optm/util/Muon_util.py
adv_optm/util/OrthoGrad.py
adv_optm/util/__init__.py
adv_optm/util/factorization_util.py
adv_optm/util/lion_k.py
adv_optm/util/param_update.py
adv_optm/util/update_util.py
adv_optm-2.2.0.dist-info/licenses/LICENSE
adv_optm-2.2.0.dist-info/METADATA
adv_optm-2.2.0.dist-info/WHEEL
adv_optm-2.2.0.dist-info/top_level.txt
adv_optm-2.2.0.dist-info/RECORD
